.todo
COPYING
MANIFEST.in
README
setup.py
pyndexter/__init__.py
pyndexter/test.py
pyndexter/util.py
pyndexter.egg-info/PKG-INFO
pyndexter.egg-info/SOURCES.txt
pyndexter.egg-info/dependency_links.txt
pyndexter.egg-info/top_level.txt
pyndexter/indexers/__init__.py
pyndexter/indexers/builtin.py
pyndexter/indexers/hype.py
pyndexter/indexers/hyperestraier.py
pyndexter/indexers/lucene.py
pyndexter/indexers/lupy.py
pyndexter/indexers/mock.py
pyndexter/indexers/pyndex.py
pyndexter/indexers/swishe.py
pyndexter/indexers/tests.py
pyndexter/indexers/xapian.py
pyndexter/sources/__init__.py
pyndexter/sources/file.py
pyndexter/sources/metasource.py
pyndexter/sources/mock.py
pyndexter/stemmers/__init__.py
pyndexter/stemmers/porter.py
pyndexter/stemmers/snowball.py
pyndexter/tests/__init__.py
pyndexter/tests/corpus.py
pyndexter/tests/excerpt.py
pyndexter/tests/framework.py
pyndexter/tests/unicode_corpus.py
