Metadata-Version: 1.0
Name: pyndexter
Version: 0.2
Summary: An abstraction layer for full-text indexing engines.
Home-page: http://swapoff.org/pyndexter
Author: Alec Thomas
Author-email: alec@swapoff.org
License: BSD
Download-URL: http://swapoff.org/pyndexter
Platform: any
Classifier: Development Status :: 3 - Alpha
Classifier: Environment :: Plugins
Classifier: Intended Audience :: Developers
Classifier: License :: OSI Approved :: BSD License
Classifier: Operating System :: OS Independent
Classifier: Topic :: Software Development :: Libraries
